[
  {
    "title": " كم عدد سور القرآن ؟",
    "answer_1": "110",
    "answer_2": "120",
    "answer_3": "112",
    "answer_4": "114",
    "right_answer": "20"
  },
  {
    "title": " What Is your Name",
    "answer_1": "Mohamed ",
    "answer_2": "Ali",
    "answer_3": "Ibraher",
    "answer_4": "Moamen",
    "right_answer": "Moamen"
  },
  {
    "title": " How Old Are You",
    "answer_1": "10",
    "answer_2": "20",
    "answer_3": "30",
    "answer_4": "50",
    "right_answer": "20"
  },
  {
    "title": " What Is your ",
    "answer_1": "Mohamed ",
    "answer_2": "Ali",
    "answer_3": "Ibraher",
    "answer_4": "Moamen",
    "right_answer": "Moamen"
  },
  {
    "title": " How Old Are You",
    "answer_1": "10",
    "answer_2": "20",
    "answer_3": "30",
    "answer_4": "50",
    "right_answer": "20"
  },
  {
    "title": " Can You Property",
    "answer_1": "Mohamed ",
    "answer_2": "Ali",
    "answer_3": "Ibraher",
    "answer_4": "Moamen",
    "right_answer": "Moamen"
  }
]
